python2algeomath/AlgeoMathBlockBuilder.py
python2algeomath/__init__.py
python2algeomath-0.0.9.dist-info/METADATA
python2algeomath-0.0.9.dist-info/WHEEL
python2algeomath-0.0.9.dist-info/top_level.txt
python2algeomath-0.0.9.dist-info/RECORD
