Metadata-Version: 2.1
Name: python2algeomath
Version: 0.0.9
Summary: to be helpful python code for Math Teacher
Home-page: https://github.com/kimkyubong/python2algeomath
Author: KimKyuBong
Author-email: tfm0405@gmail.com
Classifier: Programming Language :: Python :: 3
Classifier: License :: OSI Approved :: MIT License
Classifier: Operating System :: OS Independent
Requires-Python: >=3.8
